README.md
setup.py
commons/__init__.py
commons/common.py
commons/webclient.py
gcprofiler/__init__.py
gcprofiler/gc_profiler.py
heap/__init__.py
heap/heap_dump_profiler.py
log/__init__.py
log/log_profiler.py
log/ycrash_logger.py
logger/__init__.py
logger/logger.py
memory/__init__.py
memory/memory_leak.py
process/__init__.py
process/process_profiler.py
system/__init__.py
system/system_commands.py
system/system_info.py
system/system_profiler.py
threads/__init__.py
threads/thread_profiler.py
ycrash/__init__.py
ycrash/profiler.py
ycrash_profiler_dev.egg-info/PKG-INFO
ycrash_profiler_dev.egg-info/SOURCES.txt
ycrash_profiler_dev.egg-info/dependency_links.txt
ycrash_profiler_dev.egg-info/requires.txt
ycrash_profiler_dev.egg-info/top_level.txt